AUTHORS.rst
CONTRIBUTING.rst
HISTORY.rst
LICENSE
MANIFEST.in
README.rst
setup.cfg
setup.py
versioneer.py
docs/Makefile
docs/authors.rst
docs/conf.py
docs/contributing.rst
docs/history.rst
docs/index.rst
docs/installation.rst
docs/make.bat
docs/readme.rst
docs/usage.rst
keyedlist/__init__.py
keyedlist/_version.py
keyedlist/cli.py
keyedlist/keyedlist.py
keyedlist.egg-info/PKG-INFO
keyedlist.egg-info/SOURCES.txt
keyedlist.egg-info/dependency_links.txt
keyedlist.egg-info/entry_points.txt
keyedlist.egg-info/requires.txt
keyedlist.egg-info/top_level.txt
tests/__init__.py
tests/test_keyedlist.py
tests/test_keyedlist.py~