Metadata-Version: 1.1
Name: keyedlist
Version: 0.1
Summary: keyedlist implementation for python
Home-page: https://github.com/vanangamudi/keyedlist
Author: Pa Mu Selvakumar
Author-email: selva.developer@gmail.com
License: MIT
Platform: UNKNOWN
Classifier: Development Status :: 2 - Pre-Alpha
Classifier: Intended Audience :: Developers
Classifier: License :: OSI Approved :: MIT License
Classifier: Natural Language :: English
Classifier: Programming Language :: Python :: 2
Classifier: Programming Language :: Python :: 2.7
Classifier: Programming Language :: Python :: 3
Classifier: Programming Language :: Python :: 3.3
Classifier: Programming Language :: Python :: 3.4
Classifier: Programming Language :: Python :: 3.5
